pyfoobar/__about__.py
pyfoobar/__init__.py
pyfoobar/cli.py
pyfoobar/main.py
pyfoobar-0.0.7.dist-info/LICENSE
pyfoobar-0.0.7.dist-info/METADATA
pyfoobar-0.0.7.dist-info/WHEEL
pyfoobar-0.0.7.dist-info/entry_points.txt
pyfoobar-0.0.7.dist-info/top_level.txt
pyfoobar-0.0.7.dist-info/RECORD
