Metadata-Version: 2.1
Name: pyfoobar
Version: 0.0.7
Summary: Best practices for Python projects
Author-email: Nico Schlömer <nico.schloemer@gmail.com>
License: The MIT License (MIT)
Project-URL: Code, https://github.com/nschloe/pyfoobar
Project-URL: Issues, https://github.com/nschloe/pyfoobar/issues
Classifier: Development Status :: 4 - Beta
Classifier: Intended Audience :: Science/Research
Classifier: License :: OSI Approved :: MIT License
Classifier: Operating System :: OS Independent
Classifier: Programming Language :: Python
Classifier: Programming Language :: Python :: 3
Classifier: Programming Language :: Python :: 3.7
Classifier: Programming Language :: Python :: 3.8
Classifier: Programming Language :: Python :: 3.9
Classifier: Programming Language :: Python :: 3.10
Classifier: Programming Language :: Python :: 3.11
Classifier: Topic :: Utilities
Requires-Python: >=3.7
License-File: LICENSE
